gcheat/__init__.py
gcheat/sheets.py
sheets/__init__.py
gcheat-0.0.1.dist-info/LICENSE
gcheat-0.0.1.dist-info/METADATA
gcheat-0.0.1.dist-info/WHEEL
gcheat-0.0.1.dist-info/top_level.txt
gcheat-0.0.1.dist-info/RECORD
